{
  "name": "d3-queue",
  "description": "Evaluate asynchronous tasks with configurable concurrency.",
  "main": "d3-queue.js",
  "license": "BSD-3-Clause",
  "ignore": [],
  "homepage": "https://github.com/d3/d3-queue-bower",
  "version": "3.0.3",
  "_release": "3.0.3",
  "_resolution": {
    "type": "version",
    "tag": "v3.0.3",
    "commit": "275b419aa5b5d830b3f8e43f1677fd38ff393599"
  },
  "_source": "https://github.com/d3/d3-queue-bower.git",
  "_target": "~3.0.3",
  "_originalSource": "queue-async",
  "_direct": true
}